datatoolbelt/__init__.py
datatoolbelt/pandastools.py
datatoolbelt-0.3.0.dist-info/LICENSE
datatoolbelt-0.3.0.dist-info/LICENSES/PANDAS_LICENSE
datatoolbelt-0.3.0.dist-info/LICENSES/BUMBAG_LICENSE
datatoolbelt-0.3.0.dist-info/WHEEL
datatoolbelt-0.3.0.dist-info/METADATA
datatoolbelt-0.3.0.dist-info/RECORD
