Metadata-Version: 2.1
Name: datatoolbelt
Version: 0.3.0
Summary: A package for data utility functions.
Home-page: https://github.com/estripling/datatoolbelt
License: BSD 3-Clause
Keywords: datatoolbelt
Author: datatoolbelt Developers
Requires-Python: >=3.8,<4.0
Classifier: License :: Other/Proprietary License
Classifier: Programming Language :: Python :: 3
Classifier: Programming Language :: Python :: 3.8
Classifier: Programming Language :: Python :: 3.9
Classifier: Programming Language :: Python :: 3.10
Classifier: Programming Language :: Python :: 3
Classifier: Programming Language :: Python :: 3.10
Classifier: Programming Language :: Python :: 3.8
Classifier: Programming Language :: Python :: 3.9
Requires-Dist: bumbag (>=3.1.1,<4.0.0)
Requires-Dist: pandas (>=1.4.4,<2.0.0)
Project-URL: Documentation, https://datatoolbelt.readthedocs.io/en/stable/
Project-URL: Repository, https://github.com/estripling/datatoolbelt
